odoo/addons/l10n_ar_bank/README.rst
odoo/addons/l10n_ar_bank/__init__.py
odoo/addons/l10n_ar_bank/__manifest__.py
odoo/addons/l10n_ar_bank/data/res_bank.xml
odoo/addons/l10n_ar_bank/i18n/l10n_ar_bank.pot
odoo/addons/l10n_ar_bank/readme/CONTRIBUTORS.rst
odoo/addons/l10n_ar_bank/readme/DESCRIPTION.rst
odoo/addons/l10n_ar_bank/static/description/icon.png
odoo/addons/l10n_ar_bank/static/description/index.html
odoo_addon_l10n_ar_bank-16.0.1.0.0.1.dist-info/METADATA
odoo_addon_l10n_ar_bank-16.0.1.0.0.1.dist-info/WHEEL
odoo_addon_l10n_ar_bank-16.0.1.0.0.1.dist-info/top_level.txt
odoo_addon_l10n_ar_bank-16.0.1.0.0.1.dist-info/RECORD
